MANIFEST.in
README.md
setup.py
baimomcsm_api/__init__.py
baimomcsm_api/applications.py
baimomcsm_api/baimomcsm_error.py
baimomcsm_api/common.py
baimomcsm_api/files.py
baimomcsm_api/log_writer.py
baimomcsm_api/request_sender.py
baimomcsm_api/users.py
baimomcsm_api.egg-info/PKG-INFO
baimomcsm_api.egg-info/SOURCES.txt
baimomcsm_api.egg-info/dependency_links.txt
baimomcsm_api.egg-info/requires.txt
baimomcsm_api.egg-info/top_level.txt